shodh_memory/__init__.py
shodh_memory/client.py
shodh_memory/integrations/__init__.py
shodh_memory/integrations/langchain.py
shodh_memory/integrations/llamaindex.py
shodh_memory/shodh_memory.abi3.so
shodh_memory-0.1.75.dist-info/METADATA
shodh_memory-0.1.75.dist-info/WHEEL
shodh_memory-0.1.75.dist-info/licenses/LICENSE
shodh_memory-0.1.75.dist-info/RECORD
shodh_memory/lib/libonnxruntime.dylib
shodh_memory/models/bert-tiny-ner/model.onnx
shodh_memory/models/bert-tiny-ner/tokenizer.json
shodh_memory/models/minilm-l6/model_quantized.onnx
shodh_memory/models/minilm-l6/tokenizer.json
