Metadata-Version: 2.4
Name: shodh-memory
Version: 0.1.75
Classifier: Development Status :: 4 - Beta
Classifier: Intended Audience :: Developers
Classifier: Intended Audience :: Science/Research
Classifier: License :: OSI Approved :: Apache Software License
Classifier: Programming Language :: Python :: 3
Classifier: Programming Language :: Python :: 3.8
Classifier: Programming Language :: Python :: 3.9
Classifier: Programming Language :: Python :: 3.10
Classifier: Programming Language :: Python :: 3.11
Classifier: Programming Language :: Python :: 3.12
Classifier: Programming Language :: Python :: 3.13
Classifier: Programming Language :: Rust
Classifier: Topic :: Scientific/Engineering :: Artificial Intelligence
Classifier: Topic :: Software Development :: Libraries
License-File: LICENSE
Summary: Local-first AI memory system for robotics, drones, and edge AI - 100% offline capable
Keywords: memory,ai,edge-computing,robotics,drones,rag,vector-database,offline,ros2,autonomous,navigation,gps,spatial,mission-tracking,sensor-data
Home-Page: https://github.com/varun29ankuS/shodh-memory
Author-email: Shodh Team <29.varuns@gmail.com>
License: Apache-2.0
Requires-Python: >=3.8
Project-URL: Bug Tracker, https://github.com/varun29ankuS/shodh-memory/issues
Project-URL: Documentation, https://www.shodh-rag.com/memory
Project-URL: Homepage, https://www.shodh-rag.com/memory
Project-URL: Repository, https://github.com/varun29ankuS/shodh-memory
